augment_atoms/__init__.py
augment_atoms-0.1.0.dist-info/METADATA
augment_atoms-0.1.0.dist-info/WHEEL
augment_atoms-0.1.0.dist-info/entry_points.txt
augment_atoms-0.1.0.dist-info/RECORD
