Metadata-Version: 2.4
Name: augment-atoms
Version: 0.1.0
Summary: Add your description here
Requires-Python: >=3.9
Requires-Dist: ase>=3.25.0
Requires-Dist: dacite>=1.9.2
Requires-Dist: data2objects>=0.1.0
Requires-Dist: load-atoms>=0.3.9
Requires-Dist: vesin>=0.3.3
